BR.v
module BR (
    input wire clk,                 // Señal de reloj
    input wire [4:0] a1,            // Dirección del primer registro a leer
    input wire [4:0] a2,            // Dirección del segundo registro a leer
    input wire [4:0] a3,            // Dirección del registro a escribir
    input wire [31:0] wd3,          // Datos a escribir
    input wire we3,                 // Habilitación de escritura
    output wire [31:0] rd1,         // Salida: Contenido del registro a1
    output wire [31:0] rd2          // Salida: Contenido del registro a2
);

    // Definición de la memoria de registros (32 registros de 32 bits)
    reg [31:0] registers [0:31];

    // Inicialización de registros
    integer i;
    initial begin
        for (i = 0; i < 32; i = i + 1) begin
            registers[i] = 32'b0;   // Inicializo todos los registros en 0
        end

    end

    // Lógica para escribir en los registros
    always @(posedge clk) begin
        if (we3 && a3 != 0) begin
            registers[a3] <= wd3;  // Escribir en el registro a3 si we3 está habilitado y no es el registro 0
        end

    end

    // Lectura asíncrona de los registros
    assign rd1 = registers[a1]; // El registro 0 siempre devuelve 0
    assign rd2 = registers[a2]; // El registro 0 siempre devuelve 0

endmodule

BR_tb.v
`define DUMPSTR(x) `"x.vcd`" ///es para crear una funcion que crea ese archivo para usar en el gtkwire
`timescale 100 ns/10 ns ///escala de tiempo
module BR_tb();
    parameter duration=10;
    reg clk=0; ///inicializo en cero logico
    always #1 clk=~clk;  ///cada media unidad de tiempo le cambiamos su valor por su negado
    

    reg [4:0] test_a1;
    reg [4:0] test_a2;
    reg [4:0] test_a3;
    reg [31:0] test_wd;
    reg test_we;
    wire [31:0] test_rd1;
    wire [31:0] test_rd2;
    //defino las entradas
 //defino la salida

BR uut_br(
    .clk(clk),
    .a1(test_a1),
    .a2(test_a2),
    .a3(test_a3),
    .wd3(test_wd),
    .we3(test_we),
    .rd1(test_rd1),
    .rd2(test_rd2)
);
initial begin
    $dumpfile(`DUMPSTR(`VCD_OUTPUT));
    $dumpvars(0,BR_tb);
        #2
        test_we=0;
        test_a1=5'b00000;
        test_a2=5'b00101;
        #2
        test_we=0;
         test_a1=5'b00100;
        test_a2=5'b11111;
        #2
        test_we=1;
        test_a3=5'b00100;
        test_wd=32'b00000000000000000000000000000100;
        #2
        test_a3=5'b00101;
         test_wd=32'b00000000000000000000000000001000;
        #2
          test_we=0;
        test_a1=5'b00100;
        test_a2=5'b00101;


   #(duration) $display ("Fin de la simulacion");
    $finish;
end
endmodule

BR_tb.vcd
$date
	Mon Nov 18 10:17:15 2024
$end
$version
	Icarus Verilog
$end
$timescale
	1ps
$end
$scope module BR_tb $end
$var wire 32 ! test_rd2 [31:0] $end
$var wire 32 " test_rd1 [31:0] $end
$var parameter 32 # duration $end
$var reg 1 $ clk $end
$var reg 5 % test_a1 [4:0] $end
$var reg 5 & test_a2 [4:0] $end
$var reg 5 ' test_a3 [4:0] $end
$var reg 32 ( test_wd [31:0] $end
$var reg 1 ) test_we $end
$scope module uut_br $end
$var wire 5 * a1 [4:0] $end
$var wire 5 + a2 [4:0] $end
$var wire 5 , a3 [4:0] $end
$var wire 1 $ clk $end
$var wire 32 - wd3 [31:0] $end
$var wire 1 ) we3 $end
$var reg 32 . rd1 [31:0] $end
$var reg 32 / rd2 [31:0] $end
$var integer 32 0 i [31:0] $end
$upscope $end
$upscope $end
$enddefinitions $end
$comment Show the parameter values. $end
$dumpall
b1010 #
$end
#0
$dumpvars
b100000 0
bx /
bx .
bx -
bx ,
bx +
bx *
x)
bx (
bx '
bx &
bx %
0$
bx "
bx !
$end
#100000
1$
#200000
0$
b101 &
b101 +
b0 %
b0 *
0)
#300000
b0 !
b0 /
b0 "
b0 .
1$
#400000
0$
b11111 &
b11111 +
b100 %
b100 *
#500000
1$
#600000
0$
b100 (
b100 -
b100 '
b100 ,
1)
#700000
1$
#800000
0$
b1000 (
b1000 -
b101 '
b101 ,
#900000
1$
#1000000
0$
b101 &
b101 +
0)
#1100000
b1000 !
b1000 /
b100 "
b100 .
1$
