mux2x1.v
module Mux2x1 (
    input [31:0] e1,
    input [31:0] e2, //para el 1
    input sel,
    output [31:0] salMux
);
    assign salMux = sel ? e2 : e1;
endmodule

Adder.v
module Adder (
    input [31:0] op1,
    input [31:0] op2,
    output [31:0] res
);
    assign res = op1 + op2;
endmodule

DM.v
module DM (
    input wire clk,
    input wire [4:0] addresDM,
    input wire [31:0] wd,
    input wire we,
    output reg [31:0] rd
);
    // Memoria de 32 palabras de 32 bits cada una
    reg [31:0] memory [0:31];

    // Escritura en memoria
    always @(posedge clk) begin
        if (we) begin
            memory[addresDM] <= wd;
        end
    end

    // Lectura de memoria (asíncrona)
    always @(*) begin
        rd = memory[addresDM];
    end
endmodule

ALU.v
module ALU (
    input [31:0] srcA,
    input [31:0] srcB,
    input [2:0] ALUControl,
    output reg [31:0] result,
    output reg zero
);

    always @(*) begin
        case (ALUControl)
            3'b000: result = srcA + srcB;    // ADD
            3'b001: result = srcA - srcB;    // SUB
            3'b010: result = srcA & srcB;    // AND
            3'b011: result = srcA | srcB;    // OR
            3'b100: result = (srcA < srcB) ? 1 : 0; // SLT
            default: result = 0;
        endcase
        zero = (result == 0);
    end
endmodule

SE.v
module SE (
    input [24:0] inm,
    input [1:0] src,
    output reg [31:0] inmExt
);

    always @(*) begin
        case (src)
            2'b00: inmExt = {{20{inm[31]}}, inm[31:20]};                   // ii0
            2'b01: inmExt = {{20{inm[31]}}, inm[31:25], inm[11:7]};        // is1
            2'b10: inmExt = {{19{inm[31]}}, inm[31], inm[7], inm[30:25], inm[11:8], 1'b0};  // ib2
            2'b11: inmExt = {{12{inm[24]}}, inm[24:12]};                   // iu3
            default: inmExt = 32'b0;
        endcase
    end
endmodule

BR.v
module BR (
    input wire clk,
    input wire we,
    input wire [4:0] rs1, //a1
    input wire [4:0] rs2, //a2
    input wire [4:0] rd,  //a3
    input wire [31:0] writeData, //wd3
    output wire [31:0] readData1, //rd1
    output wire [31:0] readData2  //rd2
);

    reg [31:0] registers [31:0];

    // Lectura asíncrona
    assign readData1 = registers[rs1];
    assign readData2 = registers[rs2];

    // Escritura en flanco positivo del reloj
    always @(posedge clk) begin
        if (we && rd != 5'b0) // Registro 0 es siempre 0
            registers[rd] <= writeData;
    end

    // Inicializar registros para simulación
    integer i;
    initial begin
        for (i = 0; i < 32; i = i + 1) begin
            registers[i] = 32'b0;
        end
    end
endmodule

rom.v
module rom (
    input wire [4:0] address,     // Dirección de la memoria ROM
    output reg [31:0] data        // Instrucción de salida
);

    // Declaración de contenido de la memoria ROM
    reg [31:0] memory [0:31];

    // Inicialización de la memoria ROM con las instrucciones proporcionadas
    initial begin
    
        memory[0]  = 32'h00300413; // addi s0, zero, 3
        memory[1]  = 32'h00100493; // addi s1, zero, 1
        memory[2]  = 32'h01000913; // addi s2, zero, 16
        memory[3]  = 32'h009462b3; // or t0, s0, s1
        memory[4]  = 32'h00947333; // and t1, s0, s1
        memory[5]  = 32'h009403b3; // add t2, s0, s1
        memory[6]  = 32'h40940e33; // sub t3, s0, s1
        memory[7]  = 32'h40848eb3; // sub t4, s1, s0
        memory[8]  = 32'h00942f33; // slt t5, s0, s1
        memory[9]  = 32'h0084afb3; // slt t6, s1, s0
        memory[10] = 32'h01d4afb3; // slt t6, s1, t4
        memory[11] = 32'h00100293; // addi t0, zero, 1
        memory[12] = 32'h00000313; // addi t1, zero, 0
        memory[13] = 32'h01228863; // beq t0, s2, sal1
        memory[14] = 32'h005282b3; // add t0, t0, t0
        memory[15] = 32'h00130313; // addi t1, t1, 1
        memory[16] = 32'hff5ff06f; // j while
        memory[17] = 32'h000004b3; // add s1, zero, zero
        memory[18] = 32'h00000293; // addi t0, zero, 0
        memory[19] = 32'h00a00313; // addi t1, zero, 10
        memory[20] = 32'h00628463; // beq t0, t1, sal2
        memory[21] = 32'h008484b3; // add s1, s1, s0
        memory[22] = 32'h00128293; // addi t0, t0, 1
        memory[23] = 32'hff5ff06f; // j for
        memory[24] = 32'h00802023; // sw s0, 0(zero)
        memory[25] = 32'h00902223; // sw s1, 4(zero)
        memory[26] = 32'h01202423; // sw s2, 8(zero)
        memory[27] = 32'h00002283; // lw t0, 0(zero)
        memory[28] = 32'h00402303; // lw t1, 4(zero)
        memory[29] = 32'h00802383; // lw t2, 8(zero)
        // Direcciones restantes en 0 para completar la ROM
        memory[30] = 32'h00000000; 
        memory[31] = 32'h00000000;
    end

    // Proceso de lectura de la ROM
    always @(*) begin
        data = memory[address/4]; // Leer datos de la dirección de entrada
    end
endmodule

PC.v
module PC (
    input wire clk,
    input wire reset,
    input wire [31:0] pcNext,
    output reg [31:0] pc
);
    always @(posedge clk or posedge reset) begin
        if (reset)
            pc <= 0;
        else
            pc <= pcNext;
    end
endmodule

dataPath.v
module dataPath (
    input wire clk,
    input wire reset,
    input wire branch, aluSrc, memWrite, regWrite, pcSrc,
    input wire [1:0] resSrc, inmSrc,
    input wire [2:0] ALUcontrol,
    output wire zero,
    output wire [31:0] pc,
    output wire [31:0] aluResult, // Salida de la ALU para pruebas
    output wire [31:0] writeData  // Dato a escribir en memoria
);

    // Señales internas necesarias
    wire [31:0] pcNext, pcPlus4, branchTarget, signExtImm;
    wire [31:0] rd1, rd2, srcb, readData, result,instructionrom;
    
    // Registro del Contador de Programa (PC)
    PC pc_reg (
        .clk(clk),
        .reset(reset),
        .pcNext(pcNext),
        .pc(pc)
    );

    // Memoria de Instrucciones
    rom instructionMemory (
        .address(pc[4:0]),
        .data(instructionrom)
    );

    // Banco de Registros (BR)
    BR regFile (
        .clk(clk),
        .we(regWrite),
        .rs1(instructionrom[19:15]),
        .rs2(instructionrom[24:20]),
        .rd(instructionrom[11:7]),
        .writeData(result),
        .readData1(rd1),
        .readData2(rd2)
    );

    // Extensión de Signo (SE)
    SE sign_ext (
        .inm(instructionrom[31:7]),
        .src(inmSrc),
        .inmExt(signExtImm)
    );

    // ALU para operaciones aritmético-lógicas
    ALU alu (
        .srcA(rd1),
        .srcB(srcb),
        .ALUControl(ALUcontrol),
        .result(aluResult),
        .zero(zero)
    );
    
    // Memoria de Datos
    DM data_memory (
        .clk(clk),
        .addresDM(aluResult[4:0]),
        .wd(rd2),
        .we(memWrite),
        .rd(readData)
    );

    // Sumador para calcular PC + 4
    Adder pc_increment (
        .op1(pc),
        .op2(32'd4),
        .res(pcPlus4)
    );

    // Multiplexor para seleccionar entrada de ALU (srcB)
    Mux2x1 alu_src_mux (
        .e1(rd2),
        .e2(signExtImm),
        .sel(aluSrc),
        .salMux(srcb)
    );

    // Sumador para dirección de salto (Branch)
    Adder branch_adder (
        .op1(pc),
        .op2(signExtImm),
        .res(branchTarget)
    );

    // Selección de próxima dirección del PC (pcNext)
    Mux2x1 pc_mux (
        .e1(pcPlus4),
        .e2(branchTarget),
        .sel(pcSrc),
        .salMux(pcNext)
    );

    // Multiplexor para seleccionar dato a escribir en BR o Memoria
    Mux2x1 dm_br_mux (
        .e1(aluResult),
        .e2(readData),
        .sel(resSrc),
        .salMux(result)
    );

endmodule

inutiles/dataPath_tb.v
module dataPath_tb;
    reg clk;
    reg reset;
    reg aluSrc, memWrite, regWrite, pcSrc;
    reg [1:0] resSrc, inmSrc;
    reg [2:0] ALUcontrol;
    wire zero;
    wire [31:0] pc;
    wire [31:0] aluResult;
    wire [31:0] writeData;
    integer instruction_count = 0; // Contador de instrucciones

    // Instancia del módulo dataPath
    dataPath uut (
        .clk(clk),
        .reset(reset),
        .aluSrc(aluSrc),
        .memWrite(memWrite),
        .regWrite(regWrite),
        .pcSrc(pcSrc),
        .resSrc(resSrc),
        .inmSrc(inmSrc),
        .ALUcontrol(ALUcontrol),
        .zero(zero),
        .pc(pc),
        .aluResult(aluResult),
        .writeData(writeData)
    );

    // Generación del reloj
    always #5 clk = ~clk;

    initial begin
    $dumpfile("dataPath_tb.vcd");
        $dumpvars(0, dataPath_tb);
        // Inicialización de señales
        clk = 0;
        //reset = 1;
        aluSrc = 0;
        memWrite = 0;
        regWrite = 0;
        pcSrc = 0;
        resSrc = 2'b00;
        inmSrc = 2'b00;
        ALUcontrol = 3'b000;

        // Reset
        #10 reset = 0;

        // Configuración de control para la simulación
        while (instruction_count < 32) begin // Ajusta el límite según las instrucciones de la ROM
            @(posedge clk);
            instruction_count = instruction_count + 1;
        end

        $finish;
    end
    
endmodule

inutiles/dataPath_tb.vcd
$date
	Thu Nov 14 08:20:34 2024
$end
$version
	Icarus Verilog
$end
$timescale
	1ps
$end
$scope module dataPath_tb $end
$var wire 32 ! writeData [31:0] $end
$var wire 1 " zero $end
$var wire 32 # pc [31:0] $end
$var wire 32 $ aluResult [31:0] $end
$var reg 3 % ALUcontrol [2:0] $end
$var reg 1 & aluSrc $end
$var reg 1 ' clk $end
$var reg 2 ( inmSrc [1:0] $end
$var reg 1 ) memWrite $end
$var reg 1 * pcSrc $end
$var reg 1 + regWrite $end
$var reg 2 , resSrc [1:0] $end
$var reg 1 - reset $end
$var integer 32 . instruction_count [31:0] $end
$scope module uut $end
$var wire 3 / ALUcontrol [2:0] $end
$var wire 1 & aluSrc $end
$var wire 1 ' clk $end
$var wire 2 0 inmSrc [1:0] $end
$var wire 1 ) memWrite $end
$var wire 1 * pcSrc $end
$var wire 1 + regWrite $end
$var wire 2 1 resSrc [1:0] $end
$var wire 1 - reset $end
$var wire 32 2 writeData [31:0] $end
$var wire 1 " zero $end
$var wire 32 3 srcb [31:0] $end
$var wire 32 4 signExtImm [31:0] $end
$var wire 32 5 result [31:0] $end
$var wire 32 6 readData [31:0] $end
$var wire 32 7 rd2 [31:0] $end
$var wire 32 8 rd1 [31:0] $end
$var wire 32 9 pcPlus4 [31:0] $end
$var wire 32 : pcNext [31:0] $end
$var wire 32 ; pc [31:0] $end
$var wire 32 < instructionrom [31:0] $end
$var wire 32 = branchTarget [31:0] $end
$var wire 32 > aluResult [31:0] $end
$scope module alu $end
$var wire 3 ? ALUControl [2:0] $end
$var wire 32 @ srcB [31:0] $end
$var wire 32 A srcA [31:0] $end
$var reg 32 B result [31:0] $end
$var reg 1 " zero $end
$upscope $end
$scope module alu_src_mux $end
$var wire 1 & sel $end
$var wire 32 C salMux [31:0] $end
$var wire 32 D e2 [31:0] $end
$var wire 32 E e1 [31:0] $end
$upscope $end
$scope module branch_adder $end
$var wire 32 F res [31:0] $end
$var wire 32 G op2 [31:0] $end
$var wire 32 H op1 [31:0] $end
$upscope $end
$scope module data_memory $end
$var wire 5 I addresDM [4:0] $end
$var wire 1 ' clk $end
$var wire 1 ) we $end
$var wire 32 J wd [31:0] $end
$var reg 32 K rd [31:0] $end
$upscope $end
$scope module dm_br_mux $end
$var wire 32 L e1 [31:0] $end
$var wire 32 M e2 [31:0] $end
$var wire 1 N sel $end
$var wire 32 O salMux [31:0] $end
$upscope $end
$scope module instructionMemory $end
$var wire 5 P address [4:0] $end
$var reg 32 Q data [31:0] $end
$upscope $end
$scope module pc_increment $end
$var wire 32 R op2 [31:0] $end
$var wire 32 S res [31:0] $end
$var wire 32 T op1 [31:0] $end
$upscope $end
$scope module pc_mux $end
$var wire 32 U e1 [31:0] $end
$var wire 32 V e2 [31:0] $end
$var wire 1 * sel $end
$var wire 32 W salMux [31:0] $end
$upscope $end
$scope module pc_reg $end
$var wire 1 ' clk $end
$var wire 32 X pcNext [31:0] $end
$var wire 1 - reset $end
$var reg 32 Y pc [31:0] $end
$upscope $end
$scope module regFile $end
$var wire 1 ' clk $end
$var wire 5 Z rd [4:0] $end
$var wire 32 [ readData1 [31:0] $end
$var wire 32 \ readData2 [31:0] $end
$var wire 5 ] rs1 [4:0] $end
$var wire 5 ^ rs2 [4:0] $end
$var wire 1 + we $end
$var wire 32 _ writeData [31:0] $end
$var integer 32 ` i [31:0] $end
$upscope $end
$scope module sign_ext $end
$var wire 25 a inm [24:0] $end
$var wire 2 b src [1:0] $end
$var reg 32 c inmExt [31:0] $end
$upscope $end
$upscope $end
$upscope $end
$enddefinitions $end
$comment Show the parameter values. $end
$dumpall
$end
#0
$dumpvars
bx00000 c
b0 b
b110000000001000 a
b100000 `
b0 _
b11 ^
b0 ]
b0 \
b0 [
b1000 Z
b0 Y
b100 X
b100 W
bx V
b100 U
b0 T
b100 S
b100 R
b1100000000010000010011 Q
b0 P
b0 O
0N
bx M
b0 L
bx K
b0 J
b0 I
b0 H
bx00000 G
bx F
b0 E
bx00000 D
b0 C
b0 B
b0 A
b0 @
b0 ?
b0 >
bx =
b1100000000010000010011 <
b0 ;
b100 :
b100 9
b0 8
b0 7
bx 6
b0 5
bx00000 4
b0 3
bz 2
b0 1
b0 0
b0 /
b0 .
1-
b0 ,
0+
0*
0)
b0 (
0'
0&
b0 %
b0 $
b0 #
1"
bz !
$end
#5
1'
#10
0'
0-
#15
b10000000001001 a
b1001 Z
b1 ^
b100000000010010010011 <
b100000000010010010011 Q
b1000 :
b1000 W
b1000 X
b100 P
b1000 9
b1000 S
b1000 U
b100 #
b100 ;
b100 H
b100 T
b100 Y
b1 .
1'
#20
0'
#25
b100000000000010010 a
b10010 Z
b10000 ^
b1000000000000100100010011 <
b1000000000000100100010011 Q
b1100 :
b1100 W
b1100 X
b1000 P
b1100 9
b1100 S
b1100 U
b1000 #
b1000 ;
b1000 H
b1000 T
b1000 Y
b10 .
1'
#30
0'
#35
b10010100011000101 a
b101 Z
b1001 ^
b1000 ]
b100101000110001010110011 <
b100101000110001010110011 Q
b10000 :
b10000 W
b10000 X
b1100 P
b10000 9
b10000 S
b10000 U
b1100 #
b1100 ;
b1100 H
b1100 T
b1100 Y
b11 .
1'
#40
0'
#45
b10010100011100110 a
b110 Z
b100101000111001100110011 <
b100101000111001100110011 Q
b10100 :
b10100 W
b10100 X
b10000 P
b10100 9
b10100 S
b10100 U
b10000 #
b10000 ;
b10000 H
b10000 T
b10000 Y
b100 .
1'
#50
0'
#55
b10010100000000111 a
b111 Z
b100101000000001110110011 <
b100101000000001110110011 Q
b11000 :
b11000 W
b11000 X
b10100 P
b11000 9
b11000 S
b11000 U
b10100 #
b10100 ;
b10100 H
b10100 T
b10100 Y
b101 .
1'
#60
0'
#65
bx01000 4
bx01000 D
bx01000 G
bx01000 c
b100000010010100000011100 a
b11100 Z
b1000000100101000000111000110011 <
b1000000100101000000111000110011 Q
b11100 :
b11100 W
b11100 X
b11000 P
b11100 9
b11100 S
b11100 U
b11000 #
b11000 ;
b11000 H
b11000 T
b11000 Y
b110 .
1'
#70
0'
#75
b100000010000100100011101 a
b11101 Z
b1000 ^
b1001 ]
b1000000100001001000111010110011 <
b1000000100001001000111010110011 Q
b100000 :
b100000 W
b100000 X
b11100 P
b100000 9
b100000 S
b100000 U
b11100 #
b11100 ;
b11100 H
b11100 T
b11100 Y
b111 .
1'
#80
0'
#85
bx00000 4
bx00000 D
bx00000 G
bx00000 c
b110000000001000 a
b1000 Z
b11 ^
b0 ]
b1100000000010000010011 <
b1100000000010000010011 Q
b100100 :
b100100 W
b100100 X
b0 P
b100100 9
b100100 S
b100100 U
b100000 #
b100000 ;
b100000 H
b100000 T
b100000 Y
b1000 .
1'
#90
0'
#95
b10000000001001 a
b1001 Z
b1 ^
b100000000010010010011 <
b100000000010010010011 Q
b101000 :
b101000 W
b101000 X
b100 P
b101000 9
b101000 S
b101000 U
b100100 #
b100100 ;
b100100 H
b100100 T
b100100 Y
b1001 .
1'
#100
0'
#105
b100000000000010010 a
b10010 Z
b10000 ^
b1000000000000100100010011 <
b1000000000000100100010011 Q
b101100 :
b101100 W
b101100 X
b1000 P
b101100 9
b101100 S
b101100 U
b101000 #
b101000 ;
b101000 H
b101000 T
b101000 Y
b1010 .
1'
#110
0'
#115
b10010100011000101 a
b101 Z
b1001 ^
b1000 ]
b100101000110001010110011 <
b100101000110001010110011 Q
b110000 :
b110000 W
b110000 X
b1100 P
b110000 9
b110000 S
b110000 U
b101100 #
b101100 ;
b101100 H
b101100 T
b101100 Y
b1011 .
1'
#120
0'
#125
b10010100011100110 a
b110 Z
b100101000111001100110011 <
b100101000111001100110011 Q
b110100 :
b110100 W
b110100 X
b10000 P
b110100 9
b110100 S
b110100 U
b110000 #
b110000 ;
b110000 H
b110000 T
b110000 Y
b1100 .
1'
#130
0'
#135
b10010100000000111 a
b111 Z
b100101000000001110110011 <
b100101000000001110110011 Q
b111000 :
b111000 W
b111000 X
b10100 P
b111000 9
b111000 S
b111000 U
b110100 #
b110100 ;
b110100 H
b110100 T
b110100 Y
b1101 .
1'
#140
0'
#145
bx01000 4
bx01000 D
bx01000 G
bx01000 c
b100000010010100000011100 a
b11100 Z
b1000000100101000000111000110011 <
b1000000100101000000111000110011 Q
b111100 :
b111100 W
b111100 X
b11000 P
b111100 9
b111100 S
b111100 U
b111000 #
b111000 ;
b111000 H
b111000 T
b111000 Y
b1110 .
1'
#150
0'
#155
b100000010000100100011101 a
b11101 Z
b1000 ^
b1001 ]
b1000000100001001000111010110011 <
b1000000100001001000111010110011 Q
b1000000 :
b1000000 W
b1000000 X
b11100 P
b1000000 9
b1000000 S
b1000000 U
b111100 #
b111100 ;
b111100 H
b111100 T
b111100 Y
b1111 .
1'
#160
0'
#165
bx00000 4
bx00000 D
bx00000 G
bx00000 c
b110000000001000 a
b1000 Z
b11 ^
b0 ]
b1100000000010000010011 <
b1100000000010000010011 Q
b1000100 :
b1000100 W
b1000100 X
b0 P
b1000100 9
b1000100 S
b1000100 U
b1000000 #
b1000000 ;
b1000000 H
b1000000 T
b1000000 Y
b10000 .
1'
#170
0'
#175
b10000000001001 a
b1001 Z
b1 ^
b100000000010010010011 <
b100000000010010010011 Q
b1001000 :
b1001000 W
b1001000 X
b100 P
b1001000 9
b1001000 S
b1001000 U
b1000100 #
b1000100 ;
b1000100 H
b1000100 T
b1000100 Y
b10001 .
1'
#180
0'
#185
b100000000000010010 a
b10010 Z
b10000 ^
b1000000000000100100010011 <
b1000000000000100100010011 Q
b1001100 :
b1001100 W
b1001100 X
b1000 P
b1001100 9
b1001100 S
b1001100 U
b1001000 #
b1001000 ;
b1001000 H
b1001000 T
b1001000 Y
b10010 .
1'
#190
0'
#195
b10010100011000101 a
b101 Z
b1001 ^
b1000 ]
b100101000110001010110011 <
b100101000110001010110011 Q
b1010000 :
b1010000 W
b1010000 X
b1100 P
b1010000 9
b1010000 S
b1010000 U
b1001100 #
b1001100 ;
b1001100 H
b1001100 T
b1001100 Y
b10011 .
1'
#200
0'
#205
b10010100011100110 a
b110 Z
b100101000111001100110011 <
b100101000111001100110011 Q
b1010100 :
b1010100 W
b1010100 X
b10000 P
b1010100 9
b1010100 S
b1010100 U
b1010000 #
b1010000 ;
b1010000 H
b1010000 T
b1010000 Y
b10100 .
1'
#210
0'
#215
b10010100000000111 a
b111 Z
b100101000000001110110011 <
b100101000000001110110011 Q
b1011000 :
b1011000 W
b1011000 X
b10100 P
b1011000 9
b1011000 S
b1011000 U
b1010100 #
b1010100 ;
b1010100 H
b1010100 T
b1010100 Y
b10101 .
1'
#220
0'
#225
bx01000 4
bx01000 D
bx01000 G
bx01000 c
b100000010010100000011100 a
b11100 Z
b1000000100101000000111000110011 <
b1000000100101000000111000110011 Q
b1011100 :
b1011100 W
b1011100 X
b11000 P
b1011100 9
b1011100 S
b1011100 U
b1011000 #
b1011000 ;
b1011000 H
b1011000 T
b1011000 Y
b10110 .
1'
#230
0'
#235
b100000010000100100011101 a
b11101 Z
b1000 ^
b1001 ]
b1000000100001001000111010110011 <
b1000000100001001000111010110011 Q
b1100000 :
b1100000 W
b1100000 X
b11100 P
b1100000 9
b1100000 S
b1100000 U
b1011100 #
b1011100 ;
b1011100 H
b1011100 T
b1011100 Y
b10111 .
1'
#240
0'
#245
bx00000 4
bx00000 D
bx00000 G
bx00000 c
b110000000001000 a
b1000 Z
b11 ^
b0 ]
b1100000000010000010011 <
b1100000000010000010011 Q
b1100100 :
b1100100 W
b1100100 X
b0 P
b1100100 9
b1100100 S
b1100100 U
b1100000 #
b1100000 ;
b1100000 H
b1100000 T
b1100000 Y
b11000 .
1'
#250
0'
#255
b10000000001001 a
b1001 Z
b1 ^
b100000000010010010011 <
b100000000010010010011 Q
b1101000 :
b1101000 W
b1101000 X
b100 P
b1101000 9
b1101000 S
b1101000 U
b1100100 #
b1100100 ;
b1100100 H
b1100100 T
b1100100 Y
b11001 .
1'
#260
0'
#265
b100000000000010010 a
b10010 Z
b10000 ^
b1000000000000100100010011 <
b1000000000000100100010011 Q
b1101100 :
b1101100 W
b1101100 X
b1000 P
b1101100 9
b1101100 S
b1101100 U
b1101000 #
b1101000 ;
b1101000 H
b1101000 T
b1101000 Y
b11010 .
1'
#270
0'
#275
b10010100011000101 a
b101 Z
b1001 ^
b1000 ]
b100101000110001010110011 <
b100101000110001010110011 Q
b1110000 :
b1110000 W
b1110000 X
b1100 P
b1110000 9
b1110000 S
b1110000 U
b1101100 #
b1101100 ;
b1101100 H
b1101100 T
b1101100 Y
b11011 .
1'
#280
0'
#285
b10010100011100110 a
b110 Z
b100101000111001100110011 <
b100101000111001100110011 Q
b1110100 :
b1110100 W
b1110100 X
b10000 P
b1110100 9
b1110100 S
b1110100 U
b1110000 #
b1110000 ;
b1110000 H
b1110000 T
b1110000 Y
b11100 .
1'
#290
0'
#295
b10010100000000111 a
b111 Z
b100101000000001110110011 <
b100101000000001110110011 Q
b1111000 :
b1111000 W
b1111000 X
b10100 P
b1111000 9
b1111000 S
b1111000 U
b1110100 #
b1110100 ;
b1110100 H
b1110100 T
b1110100 Y
b11101 .
1'
#300
0'
#305
bx01000 4
bx01000 D
bx01000 G
bx01000 c
b100000010010100000011100 a
b11100 Z
b1000000100101000000111000110011 <
b1000000100101000000111000110011 Q
b1111100 :
b1111100 W
b1111100 X
b11000 P
b1111100 9
b1111100 S
b1111100 U
b1111000 #
b1111000 ;
b1111000 H
b1111000 T
b1111000 Y
b11110 .
1'
#310
0'
#315
b100000010000100100011101 a
b11101 Z
b1000 ^
b1001 ]
b1000000100001001000111010110011 <
b1000000100001001000111010110011 Q
b10000000 :
b10000000 W
b10000000 X
b11100 P
b10000000 9
b10000000 S
b10000000 U
b1111100 #
b1111100 ;
b1111100 H
b1111100 T
b1111100 Y
b11111 .
1'
#320
0'
#325
bx00000 4
bx00000 D
bx00000 G
bx00000 c
b110000000001000 a
b1000 Z
b11 ^
b0 ]
b1100000000010000010011 <
b1100000000010000010011 Q
b10000100 :
b10000100 W
b10000100 X
b0 P
b10000100 9
b10000100 S
b10000100 U
b10000000 #
b10000000 ;
b10000000 H
b10000000 T
b10000000 Y
b100000 .
1'
